enterpriseattack/__init__.py
enterpriseattack/campaign.py
enterpriseattack/component.py
enterpriseattack/data_source.py
enterpriseattack/group.py
enterpriseattack/mitigation.py
enterpriseattack/software.py
enterpriseattack/sub_technique.py
enterpriseattack/tactic.py
enterpriseattack/technique.py
enterpriseattack/utils.py
enterpriseattack-1.0.3.dist-info/licenses/LICENSE
enterpriseattack-1.0.3.dist-info/METADATA
enterpriseattack-1.0.3.dist-info/WHEEL
enterpriseattack-1.0.3.dist-info/top_level.txt
enterpriseattack-1.0.3.dist-info/RECORD
