Metadata-Version: 2.4
Name: enterpriseattack
Version: 1.0.3
Summary: A lightweight Python module to interact with the MITRE ATT&CK® Enterprise dataset.
Home-page: https://gitlab.com/xakepnz/enterpriseattack
Author: xakepnz
Author-email: xakepnz <xakepnz@pm.me>
Project-URL: Homepage, https://gitlab.com/xakepnz/enterpriseattack
Project-URL: Documentation, https://gitlab.com/xakepnz/enterpriseattack/-/tree/main/docs
Project-URL: Issues, https://gitlab.com/xakepnz/enterpriseattack/-/issues
Project-URL: Changelog, https://gitlab.com/xakepnz/enterpriseattack/-/tree/main/CHANGELOG.md
Project-URL: Download, https://gitlab.com/xakepnz/enterpriseattack/-/releases
Keywords: mitre att&ck,att&ck enterprise,enterpriseattack,mitre python,mitre att&ck python,mitre framework,att&ck
Classifier: Development Status :: 4 - Beta
Classifier: Intended Audience :: Developers
Classifier: Intended Audience :: Information Technology
Classifier: Intended Audience :: Science/Research
Classifier: Intended Audience :: System Administrators
Classifier: Operating System :: OS Independent
Classifier: Programming Language :: Python
Classifier: Programming Language :: Python :: 3
Classifier: Programming Language :: Python :: 3 :: Only
Classifier: Programming Language :: Python :: 3.10
Classifier: Programming Language :: Python :: 3.11
Classifier: Programming Language :: Python :: 3.12
Classifier: Programming Language :: Python :: 3.13
Classifier: Topic :: Security
Classifier: Topic :: Software Development :: Libraries :: Python Modules
Classifier: Topic :: System :: Systems Administration
Classifier: Typing :: Typed
Requires-Python: >=3.10
License-File: LICENSE
Requires-Dist: ujson>=3.0.0
Requires-Dist: requests>=2.9.2
Provides-Extra: build
Requires-Dist: setuptools~=80.0; extra == "build"
Requires-Dist: wheel==0.45.1; extra == "build"
Requires-Dist: build==1.2.2.post1; extra == "build"
Requires-Dist: setuptools-scm~=8.3.1; extra == "build"
Provides-Extra: release
Requires-Dist: twine==6.1.0; extra == "release"
Requires-Dist: python-semantic-release==10.2.0; extra == "release"
Provides-Extra: test
Requires-Dist: pytest>=6.1.0; extra == "test"
Requires-Dist: pytest-cov>=2.10.1; extra == "test"
Requires-Dist: flake8>=3.7.9; extra == "test"
Requires-Dist: tox>=3.14.2; extra == "test"
Requires-Dist: coverage==4.5.4; extra == "test"
Requires-Dist: pipdeptree==2.26.1; extra == "test"
Requires-Dist: pre-commit~=4.2.0; extra == "test"
Requires-Dist: bandit==1.8.3; extra == "test"
Requires-Dist: tox~=4.25.0; extra == "test"
Requires-Dist: isort==6.0.1; extra == "test"
Requires-Dist: black==25.1.0; extra == "test"
Dynamic: author
Dynamic: home-page
Dynamic: license-file
